caql/__init__.py
caql/classes.py
caql/collapsed.py
caql/engine.py
caql/errors.py
caql/ty.py
caql-0.8.0.dist-info/LICENSE
caql-0.8.0.dist-info/WHEEL
caql-0.8.0.dist-info/METADATA
caql-0.8.0.dist-info/RECORD
